parallel_sparse_tools.libs/libgomp-a34b3233.so.1.0.0
parallel_sparse_tools/__init__.py
parallel_sparse_tools/_version.py
parallel_sparse_tools/expm_multiply_parallel_core/expm_multiply_parallel_wrapper.cpython-312-x86_64-linux-gnu.so
parallel_sparse_tools/expm_multiply_parallel_core/__init__.py
parallel_sparse_tools/expm_multiply_parallel_core/generate_source.py
parallel_sparse_tools/expm_multiply_parallel_core/expm_multiply_parallel_wrapper.cpp
parallel_sparse_tools/expm_multiply_parallel_core/expm_multiply_parallel_core.py
parallel_sparse_tools/expm_multiply_parallel_core/source/expm_multiply_parallel_impl.h
parallel_sparse_tools/expm_multiply_parallel_core/source/csr_utils.h
parallel_sparse_tools/matvec/_oputils.cpython-312-x86_64-linux-gnu.so
parallel_sparse_tools/matvec/matvec_core.py
parallel_sparse_tools/matvec/generate_oputils.py
parallel_sparse_tools/matvec/__init__.py
parallel_sparse_tools/matvec/_oputils.cpp
parallel_sparse_tools/matvec/_oputils/oputils_impl.h
parallel_sparse_tools-0.2.3.dist-info/top_level.txt
parallel_sparse_tools-0.2.3.dist-info/RECORD
parallel_sparse_tools-0.2.3.dist-info/LICENSE
parallel_sparse_tools-0.2.3.dist-info/METADATA
parallel_sparse_tools-0.2.3.dist-info/WHEEL
