Metadata-Version: 2.1
Name: parallel-sparse-tools
Version: 0.2.3
Summary: My package description
Author-email: Phillip Weinberg <weinbe58@gmail.com>
License: BSD-3-Clause
Classifier: Development Status :: 3 - Alpha
Classifier: Operating System :: Microsoft :: Windows
Classifier: Operating System :: MacOS
Classifier: Operating System :: POSIX :: Linux
Classifier: Programming Language :: Python :: 3.9
Classifier: Programming Language :: Python :: 3.10
Classifier: Programming Language :: Python :: 3.11
Classifier: Programming Language :: Python :: 3.12
Requires-Python: <3.13,>=3.9
License-File: LICENSE
Requires-Dist: numpy>=2.0.0
Requires-Dist: scipy>=1.13.0
